{
  "id": "291A7054-74D5-409D-8CFF-DA419FC44157",
  "name": "G",
  "category": "GROSSBUCHSTABEN",
  "illustrations": [
    "Gabel",
    "Gitarre",
    "Glas"
  ],
  "className": "blue",
  "unlockCondition": "",
  "lineWidth": 44,
  "_lastChange": 1382512758335,
  "paths": [
    [
      {
        "x": 279.5724734042553,
        "y": 85.81648936170212,
        "isAnchor": true
      },
      {
        "x": 259.688164893617,
        "y": 75.35106382978724
      },
      {
        "x": 214.68683510638297,
        "y": 63.839095744680854,
        "isAnchor": false
      },
      {
        "x": 192.7094414893617,
        "y": 63.839095744680854,
        "isAnchor": false
      },
      {
        "x": 161.31316489361703,
        "y": 70.11835106382979,
        "isAnchor": false
      },
      {
        "x": 139.33577127659575,
        "y": 80.58377659574468,
        "isAnchor": false
      },
      {
        "x": 97.47406914893617,
        "y": 114.07313829787235,
        "isAnchor": false
      },
      {
        "x": 69.21742021276596,
        "y": 143.37632978723406,
        "isAnchor": false
      },
      {
        "x": 56.658909574468076,
        "y": 163.26063829787233,
        "isAnchor": false
      },
      {
        "x": 42.00731382978723,
        "y": 197.7965425531915,
        "isAnchor": false
      },
      {
        "x": 28.402260638297864,
        "y": 245.9375,
        "isAnchor": false
      },
      {
        "x": 23.16954787234042,
        "y": 303.49734042553195,
        "isAnchor": false
      },
      {
        "x": 24.21609042553191,
        "y": 352.68484042553195,
        "isAnchor": false
      },
      {
        "x": 35.72805851063829,
        "y": 415.4773936170213,
        "isAnchor": false
      },
      {
        "x": 44.10039893617021,
        "y": 440.59441489361706,
        "isAnchor": false
      },
      {
        "x": 52.472739361702125,
        "y": 455.2460106382979,
        "isAnchor": false
      },
      {
        "x": 80.72938829787233,
        "y": 485.59574468085106,
        "isAnchor": false
      },
      {
        "x": 104.7998670212766,
        "y": 499.20079787234044,
        "isAnchor": false
      },
      {
        "x": 130.96343085106383,
        "y": 507.57313829787233,
        "isAnchor": false
      },
      {
        "x": 165.49933510638297,
        "y": 511.75930851063833,
        "isAnchor": false
      },
      {
        "x": 201.0817819148936,
        "y": 507.57313829787233,
        "isAnchor": false
      },
      {
        "x": 224.1057180851064,
        "y": 500.24734042553195,
        "isAnchor": false
      },
      {
        "x": 258.64162234042556,
        "y": 482.4561170212766,
        "isAnchor": false
      },
      {
        "x": 287.9448138297872,
        "y": 457.33909574468083,
        "isAnchor": false
      },
      {
        "x": 305.7360372340425,
        "y": 434.3151595744681,
        "isAnchor": false
      },
      {
        "x": 327.7134308510638,
        "y": 398.73271276595744,
        "isAnchor": false
      },
      {
        "x": 343.41156914893617,
        "y": 351.63829787234044,
        "isAnchor": false
      },
      {
        "x": 349.69082446808505,
        "y": 318.1489361702128,
        "isAnchor": false
      },
      {
        "x": 347.5977393617021,
        "y": 277.33377659574467,
        "isAnchor": false
      },
      {
        "x": 343.41156914893617,
        "y": 273.1476063829787,
        "isAnchor": true
      },
      {
        "x": 264.92087765957444,
        "y": 277.33377659574467
      },
      {
        "x": 237.71077127659575,
        "y": 272.1010638297872,
        "isAnchor": true
      }
    ]
  ]
}